fileenc_openssl/__init__.py
fileenc_openssl/commands.py
fileenc_openssl/enc_dec.py
fileenc_openssl/misc.py
fileenc_openssl-1.3.0.dist-info/DESCRIPTION.rst
fileenc_openssl-1.3.0.dist-info/METADATA
fileenc_openssl-1.3.0.dist-info/RECORD
fileenc_openssl-1.3.0.dist-info/WHEEL
fileenc_openssl-1.3.0.dist-info/entry_points.txt
fileenc_openssl-1.3.0.dist-info/metadata.json
fileenc_openssl-1.3.0.dist-info/top_level.txt
