Metadata-Version: 2.0
Name: fileenc-openssl
Version: 1.3.0
Summary: allows one to easily encrypt and decrypt files symmetrically using openssl and python3
Home-page: https://github.com/mverleg/fileenc_openssl
Author: (the author)
Author-email: mdilligaf@gmail.com
License: Revised BSD License (LICENSE.txt)
Keywords: encryption,openssl
Platform: UNKNOWN
Classifier: Development Status :: 5 - Production/Stable
Classifier: Natural Language :: English
Classifier: License :: OSI Approved :: BSD License
Classifier: Programming Language :: Python
Classifier: Programming Language :: Python :: 3
Classifier: Programming Language :: Python :: 3.3
Classifier: Programming Language :: Python :: 3.4
Classifier: Programming Language :: Python :: 3.5
